ephem/__init__.py
ephem/get_ephem.py
ephem/tests/__init__.py
ephem/tests/test_get_ephem.py
planetaryToolkit-0.0.4.dist-info/LICENSE.txt
planetaryToolkit-0.0.4.dist-info/METADATA
planetaryToolkit-0.0.4.dist-info/WHEEL
planetaryToolkit-0.0.4.dist-info/top_level.txt
planetaryToolkit-0.0.4.dist-info/RECORD
